sum_dict/__init__.py
sum_dict-0.0.1.dist-info/METADATA
sum_dict-0.0.1.dist-info/WHEEL
sum_dict-0.0.1.dist-info/top_level.txt
sum_dict-0.0.1.dist-info/RECORD
